test_project/manage.py
test_project/settings.py
test_project/__init__.py
test_project/wsgi.py
test_project/test_runner.py
incuna_groups-4.1.0.dist-info/WHEEL
incuna_groups-4.1.0.dist-info/RECORD
incuna_groups-4.1.0.dist-info/METADATA
incuna_groups-4.1.0.dist-info/metadata.json
incuna_groups-4.1.0.dist-info/DESCRIPTION.rst
incuna_groups-4.1.0.dist-info/top_level.txt
groups/models.py
groups/_apps_base.py
groups/__init__.py
groups/admin.py
groups/urls.py
groups/managers.py
groups/forms.py
groups/apps.py
groups/migrations/0011_textcomment.py
groups/migrations/0006_alter_related_names.py
groups/migrations/0003_comment.py
groups/migrations/__init__.py
groups/migrations/0014_discussion_ignorers.py
groups/migrations/0015_unrequire_m2ms.py
groups/migrations/0016_attachedfile.py
groups/migrations/0017_remove_file_comment.py
groups/migrations/0004_modify_comment_fields.py
groups/migrations/0013_update_filecomment_upload_update_basecomment_related_name.py
groups/migrations/0018_textcomment_managers.py
groups/migrations/0009_comment_polymorphic_ctype.py
groups/migrations/0007_change_ordering.py
groups/migrations/0012_filecomment.py
groups/migrations/0001_initial.py
groups/migrations/0008_comment_state.py
groups/migrations/0002_discussion.py
groups/migrations/0005_add_comment_ordering.py
groups/migrations/0010_create_comment_base_class.py
groups/templatetags/__init__.py
groups/templatetags/groups_tags.py
groups/tests/test_views_discussions.py
groups/tests/test_models.py
groups/tests/__init__.py
groups/tests/urls.py
groups/tests/factories.py
groups/tests/test_admin.py
groups/tests/test_views_groups.py
groups/tests/test_views_subscriptions.py
groups/tests/test_views_comments.py
groups/tests/test_apps_base.py
groups/tests/test_urls.py
groups/tests/test_forms.py
groups/tests/test_groups_functional.py
groups/tests/test_managers.py
groups/tests/test_apps.py
groups/tests/utils.py
groups/tests/test_views_helpers.py
groups/tests/templates/base.html
groups/views/__init__.py
groups/views/subscriptions.py
groups/views/comments.py
groups/views/discussions.py
groups/views/groups.py
groups/views/_helpers.py
groups/templates/groups/subscribe_button_base.html
