Metadata-Version: 2.0
Name: incuna-groups
Version: 4.1.0
Summary: Generic group/forum framework.
Home-page: https://github.com/incuna/incuna-groups
Author: Incuna Ltd
Author-email: admin@incuna.com
License: UNKNOWN
Platform: UNKNOWN
Requires-Dist: django-crispy-forms (>=1.6.1,<2)
Requires-Dist: django-polymorphic (>=1.2,<1.3)
Requires-Dist: incuna-pagination (>=0.1.3,<1)
